{
    "TrackLength": "00:15:00",
    "Channels": {
        "Left": {
            "Components": [
                { "Frequency": "FrequencyRange.exprtk", ":low": 0.3, ":high": 1, ":periodicity": 31, "Pulse": "SinWithWetness.exprtk", ":wetness": 0.3 },
                { "Frequency": "320", "Pulse": "sin(x)" },
                { "Frequency": "1", "Pulse": "BoostEnvelope.exprtk", ":start": 150, ":end": 15, ":up": 5, ":top": 10, ":down": 5, ":att": 0.83 }
            ]
        },
        "Right": {
            "Components": [
                { "Frequency": "FrequencyRange.exprtk", ":low": 0.3, ":high": 1, ":periodicity": 37, "Pulse": "SinWithWetness.exprtk", ":wetness": 0.3 },
                { "Frequency": "641", "Pulse": "sin(x)" },
                { "Frequency": "1", "Pulse": "BoostEnvelope.exprtk", ":start": 150, ":end": 15, ":up": 5, ":top": 10, ":down": 5, ":att": 0.83 }
            ]
        }
    }
}